pydream3/__init__.py
pydream3/display.py
pydream3/font.py
pydream_led_3-0.3.1.dist-info/LICENSE
pydream_led_3-0.3.1.dist-info/METADATA
pydream_led_3-0.3.1.dist-info/WHEEL
pydream_led_3-0.3.1.dist-info/top_level.txt
pydream_led_3-0.3.1.dist-info/RECORD
